manim_beamer/__init__.py
manim_beamer/bibtex.py
manim_beamer/blocks.py
manim_beamer/images.py
manim_beamer/lists.py
manim_beamer/slides.py
manim_beamer-0.0.2.dist-info/METADATA
manim_beamer-0.0.2.dist-info/WHEEL
manim_beamer-0.0.2.dist-info/licenses/LICENSE
manim_beamer-0.0.2.dist-info/RECORD
