Metadata-Version: 2.3
Name: manim-beamer
Version: 0.0.2
Summary: Emulate LATEX beamer with Python and manim-slides.
Project-URL: Homepage, https://github.com/johnHostetter/manim-beamer
Project-URL: Issues, https://github.com/johnHostetter/manim-beamer/issues
Author-email: John Wesley Hostetter <jhostetter16@gmail.com>
License-File: LICENSE
Classifier: License :: OSI Approved :: MIT License
Classifier: Operating System :: OS Independent
Classifier: Programming Language :: Python :: 3
Requires-Python: >=3.9
